{
  "employees": [
    {
      "id": "627a071680ffc788f9ccfc6b",
      "email": "kimberley_sawyer@insectus.tienda",
      "username": "kimberley91",
      "name": "Kimberley Sawyer",
      "company": "Insectus",
      "dob": "1991-05-13",
      "address": "84 Stratford Road, Belfair, Palau",
      "location": {
        "lat": 59.647554,
        "long": -96.678203
      },
      "about": "Sit mollit eu pariatur veniam irure. Aute sit occaecat exercitation elit qui est irure consectetur do laborum officia.",
      "createdAt": "2010-05-09T05:27:06.104Z",
      "updatedAt": "2010-05-10T05:27:06.104Z"
    },
    {
      "id": "627a071612d5f6c855244ed6",
      "email": "patton_pitts@xixan.seat",
      "username": "patton89",
      "name": "Patton Pitts",
      "company": "Xixan",
      "dob": "1989-06-11",
      "address": "97 Prospect Avenue, Emory, Oklahoma",
      "location": {
        "lat": -71.715925,
        "long": -43.826148
      },
      "about": "Incididunt non sunt cillum laboris sint aliquip ad irure amet adipisicing ipsum. Eu consectetur ipsum reprehenderit tempor labore dolor ullamco non.",
      "createdAt": "2011-07-19T10:28:59.105Z",
      "updatedAt": "2011-07-20T10:28:59.105Z"
    },
    {
      "id": "627a07164abec7b2cd67d4d2",
      "email": "fowler_ware@zipak.krd",
      "username": "fowler94",
      "name": "Fowler Ware",
      "company": "Zipak",
      "dob": "1994-09-21",
      "address": "10 Monitor Street, Kohatk, Kansas",
      "location": {
        "lat": 17.825113,
        "long": -179.585803
      },
      "about": "Esse cillum non aute ea nulla. Pariatur ullamco laboris et fugiat non.",
      "createdAt": "2013-02-27T17:38:12.189Z",
      "updatedAt": "2013-02-28T17:38:12.189Z"
    },
    {
      "id": "627a0716debd2ceab0eb64e9",
      "email": "carly_ferrell@comtrail.study",
      "username": "carly88",
      "name": "Carly Ferrell",
      "company": "Comtrail",
      "dob": "1988-09-07",
      "address": "82 Perry Terrace, Blairstown, Oregon",
      "location": {
        "lat": 63.995814,
        "long": -87.170148
      },
      "about": "In pariatur sunt cillum enim id. Nisi ea officia labore velit tempor.",
      "createdAt": "2010-03-09T10:01:01.190Z",
      "updatedAt": "2010-03-10T10:01:01.190Z"
    },
    {
      "id": "627a0716ebf4f1a4a288157a",
      "email": "daisy_horne@stucco.sex",
      "username": "daisy93",
      "name": "Daisy Horne",
      "company": "Stucco",
      "dob": "1993-06-22",
      "address": "81 Franklin Street, Marbury, Wyoming",
      "location": {
        "lat": -55.655929,
        "long": 96.415839
      },
      "about": "Ad qui id sunt ut aliquip commodo commodo duis. Elit veniam duis cillum eu do dolore consectetur ipsum elit irure ut nisi pariatur veniam.",
      "createdAt": "2014-06-26T16:03:44.635Z",
      "updatedAt": "2014-06-27T16:03:44.635Z"
    },
    {
      "id": "627a07162100a581869a7328",
      "email": "knox_snow@escenta.kaufen",
      "username": "knox89",
      "name": "Knox Snow",
      "company": "Escenta",
      "dob": "1989-09-27",
      "address": "70 Lott Street, Clayville, Idaho",
      "location": {
        "lat": 37.535375,
        "long": -82.160291
      },
      "about": "Ullamco do fugiat ullamco tempor est sint ut exercitation ex tempor minim velit aliquip velit. Cillum esse tempor anim ea dolor in culpa ea.",
      "createdAt": "2012-08-29T01:47:06.348Z",
      "updatedAt": "2012-08-30T01:47:06.348Z"
    },
    {
      "id": "627a0716aba26fc5115839ed",
      "email": "ramos_dillard@digiprint.nyc",
      "username": "ramos92",
      "name": "Ramos Dillard",
      "company": "Digiprint",
      "dob": "1992-12-04",
      "address": "11 Howard Alley, Deseret, Florida",
      "location": {
        "lat": 79.451364,
        "long": 78.591327
      },
      "about": "Consectetur eu aute ea pariatur consequat voluptate commodo officia ea amet magna eiusmod anim. Adipisicing minim occaecat id est reprehenderit nostrud qui nostrud.",
      "createdAt": "2013-02-27T17:40:45.516Z",
      "updatedAt": "2013-02-28T17:40:45.516Z"
    },
    {
      "id": "627a0716eab75b3893e21e3f",
      "email": "kaitlin_frost@kindaloo.doha",
      "username": "kaitlin93",
      "name": "Kaitlin Frost",
      "company": "Kindaloo",
      "dob": "1993-09-06",
      "address": "34 Lynch Street, Wawona, New York",
      "location": {
        "lat": 43.052055,
        "long": -15.593809
      },
      "about": "Ipsum magna quis dolor voluptate veniam amet ut labore. Commodo nisi sit pariatur non ut ea sint nulla.",
      "createdAt": "2011-12-01T13:06:51.801Z",
      "updatedAt": "2011-12-02T13:06:51.801Z"
    },
    {
      "id": "627a07165ce663ef235a600e",
      "email": "oneal_holcomb@konnect.cx",
      "username": "oneal94",
      "name": "Oneal Holcomb",
      "company": "Konnect",
      "dob": "1994-04-09",
      "address": "76 Strauss Street, Tryon, South Dakota",
      "location": {
        "lat": -57.796279,
        "long": 82.125923
      },
      "about": "Esse labore ad magna sint Lorem irure sit nisi sunt laborum non magna sit. In aliquip amet sunt consectetur Lorem commodo minim.",
      "createdAt": "2011-11-14T03:16:19.656Z",
      "updatedAt": "2011-11-15T03:16:19.656Z"
    },
    {
      "id": "627a07163f49a679b8b9469c",
      "email": "deborah_dodson@medcom.dvag",
      "username": "deborah91",
      "name": "Deborah Dodson",
      "company": "Medcom",
      "dob": "1991-12-03",
      "address": "41 Billings Place, Ahwahnee, Virginia",
      "location": {
        "lat": -37.133541,
        "long": -52.824987
      },
      "about": "Eiusmod officia tempor reprehenderit pariatur minim aliquip quis in ad. Eu pariatur ad consequat voluptate est minim cillum consectetur ad consequat amet.",
      "createdAt": "2011-07-18T09:43:56.698Z",
      "updatedAt": "2011-07-19T09:43:56.698Z"
    },
    {
      "id": "627a07164d50b4284028a469",
      "email": "april_mccarthy@valpreal.saarland",
      "username": "april92",
      "name": "April Mccarthy",
      "company": "Valpreal",
      "dob": "1992-07-11",
      "address": "10 Homecrest Court, Faywood, Federated States Of Micronesia",
      "location": {
        "lat": -82.636895,
        "long": 113.496886
      },
      "about": "Ut ex minim sunt excepteur. Nisi magna velit aute velit.",
      "createdAt": "2010-04-16T02:52:09.078Z",
      "updatedAt": "2010-04-17T02:52:09.078Z"
    },
    {
      "id": "627a0716dd1ffc4ec15132fc",
      "email": "noelle_french@temorak.me",
      "username": "noelle94",
      "name": "Noelle French",
      "company": "Temorak",
      "dob": "1994-12-22",
      "address": "46 Livingston Street, Elliston, Hawaii",
      "location": {
        "lat": 29.025982,
        "long": -177.049879
      },
      "about": "Ea quis irure elit do aliqua et duis deserunt voluptate ex sunt. Consectetur incididunt amet id nostrud in ad quis veniam nostrud deserunt laboris amet dolor esse.",
      "createdAt": "2011-05-24T00:14:47.642Z",
      "updatedAt": "2011-05-25T00:14:47.642Z"
    },
    {
      "id": "627a0716eb2ecd54d16a85cc",
      "email": "deann_reynolds@acium.condos",
      "username": "deann92",
      "name": "Deann Reynolds",
      "company": "Acium",
      "dob": "1992-06-19",
      "address": "10 Newkirk Placez, Trucksville, Virgin Islands",
      "location": {
        "lat": -10.983215,
        "long": 31.348961
      },
      "about": "Velit consectetur nostrud est nulla minim ipsum. Consectetur ad commodo occaecat in reprehenderit dolore sint proident ullamco adipisicing et anim.",
      "createdAt": "2013-02-12T20:58:40.174Z",
      "updatedAt": "2013-02-13T20:58:40.174Z"
    },
    {
      "id": "627a0716ec5f797165fa0889",
      "email": "trujillo_yates@nixelt.gal",
      "username": "trujillo89",
      "name": "Trujillo Yates",
      "company": "Nixelt",
      "dob": "1989-01-16",
      "address": "89 Holt Court, Stonybrook, Iowa",
      "location": {
        "lat": -12.329589,
        "long": 70.709834
      },
      "about": "Proident pariatur aliqua cillum mollit minim laboris minim nulla cillum. Nulla proident quis velit exercitation culpa deserunt ipsum proident aute.",
      "createdAt": "2010-01-12T02:04:14.873Z",
      "updatedAt": "2010-01-13T02:04:14.873Z"
    },
    {
      "id": "627a0716ad2df84329704965",
      "email": "austin_woodward@zilencio.bharti",
      "username": "austin93",
      "name": "Austin Woodward",
      "company": "Zilencio",
      "dob": "1993-08-24",
      "address": "18 Elton Street, Toftrees, New Mexico",
      "location": {
        "lat": -85.716346,
        "long": 95.950509
      },
      "about": "Et deserunt veniam consequat consequat laboris ipsum. Excepteur incididunt qui deserunt mollit et nulla excepteur fugiat occaecat nisi laborum exercitation ut.",
      "createdAt": "2014-06-22T00:14:58.755Z",
      "updatedAt": "2014-06-23T00:14:58.755Z"
    },
    {
      "id": "627a07166c3cabb79159399f",
      "email": "gilmore_wells@eweville.bbva",
      "username": "gilmore91",
      "name": "Gilmore Wells",
      "company": "Eweville",
      "dob": "1991-03-06",
      "address": "30 Fane Court, Mammoth, Indiana",
      "location": {
        "lat": 16.773521,
        "long": -162.727572
      },
      "about": "Fugiat tempor minim laboris occaecat tempor aliquip. Laborum duis eiusmod mollit aute pariatur cillum Lorem est ipsum ipsum laborum cillum.",
      "createdAt": "2012-02-09T07:41:15.230Z",
      "updatedAt": "2012-02-10T07:41:15.230Z"
    },
    {
      "id": "627a0716f1aeea23a0fcfe94",
      "email": "sheena_armstrong@panzent.is",
      "username": "sheena89",
      "name": "Sheena Armstrong",
      "company": "Panzent",
      "dob": "1989-09-02",
      "address": "68 Harrison Place, Waikele, Washington",
      "location": {
        "lat": 51.656513,
        "long": 97.780318
      },
      "about": "Eu velit sit sunt adipisicing eiusmod est deserunt anim consectetur et enim. Dolor elit duis enim veniam non excepteur voluptate tempor culpa Lorem consequat ea.",
      "createdAt": "2013-01-21T20:23:34.147Z",
      "updatedAt": "2013-01-22T20:23:34.147Z"
    },
    {
      "id": "627a07169878109691f55506",
      "email": "rodriguez_kramer@lyria.za",
      "username": "rodriguez88",
      "name": "Rodriguez Kramer",
      "company": "Lyria",
      "dob": "1988-02-27",
      "address": "51 McKibbin Street, Golconda, Illinois",
      "location": {
        "lat": 34.284098,
        "long": 107.668907
      },
      "about": "Commodo labore culpa excepteur voluptate commodo proident esse. Reprehenderit consequat exercitation laboris commodo ullamco consequat labore consequat ex aliqua occaecat culpa sint.",
      "createdAt": "2012-01-17T10:27:31.609Z",
      "updatedAt": "2012-01-18T10:27:31.609Z"
    },
    {
      "id": "627a0716ea84e97ba364562a",
      "email": "lucia_richards@viasia.il",
      "username": "lucia93",
      "name": "Lucia Richards",
      "company": "Viasia",
      "dob": "1993-11-16",
      "address": "27 Fenimore Street, Juarez, Mississippi",
      "location": {
        "lat": -28.453519,
        "long": -117.490986
      },
      "about": "Irure commodo sint eiusmod labore veniam exercitation veniam. In officia non est ex labore non aliqua elit.",
      "createdAt": "2010-03-14T01:39:06.492Z",
      "updatedAt": "2010-03-15T01:39:06.492Z"
    },
    {
      "id": "627a07169654e59dd66d8c49",
      "email": "stevens_smith@aclima.kh",
      "username": "stevens88",
      "name": "Stevens Smith",
      "company": "Aclima",
      "dob": "1988-02-05",
      "address": "45 Beadel Street, Grandview, New Hampshire",
      "location": {
        "lat": -7.158922,
        "long": 175.370726
      },
      "about": "Ullamco duis est nisi ipsum do magna amet reprehenderit quis aliqua ex ex tempor ut. Non mollit nisi reprehenderit ipsum aute ipsum ex.",
      "createdAt": "2011-06-15T06:48:05.408Z",
      "updatedAt": "2011-06-16T06:48:05.408Z"
    },
    {
      "id": "627a071619707ce0f9ace790",
      "email": "marla_oliver@zillatide.nc",
      "username": "marla90",
      "name": "Marla Oliver",
      "company": "Zillatide",
      "dob": "1990-02-24",
      "address": "45 Bergen Court, Oberlin, Marshall Islands",
      "location": {
        "lat": 83.739636,
        "long": -146.768914
      },
      "about": "Mollit ipsum eu incididunt esse aute ut nostrud nostrud ut aliquip eu proident fugiat consectetur. Consectetur commodo proident excepteur laboris sunt adipisicing laborum dolor in culpa amet consequat in.",
      "createdAt": "2014-05-19T12:12:12.614Z",
      "updatedAt": "2014-05-20T12:12:12.614Z"
    },
    {
      "id": "627a07161ab6a93cdde59c78",
      "email": "chrystal_sparks@maxemia.cyou",
      "username": "chrystal93",
      "name": "Chrystal Sparks",
      "company": "Maxemia",
      "dob": "1993-03-28",
      "address": "93 Grace Court, Lisco, Utah",
      "location": {
        "lat": -33.984165,
        "long": -81.112266
      },
      "about": "Amet eu ullamco qui sint fugiat consectetur minim ad quis ullamco eu. Qui nostrud elit mollit voluptate ad tempor enim.",
      "createdAt": "2011-11-20T11:08:09.936Z",
      "updatedAt": "2011-11-21T11:08:09.936Z"
    },
    {
      "id": "627a0716f261b6cc4e26c9f9",
      "email": "gilbert_berg@enquility.im",
      "username": "gilbert90",
      "name": "Gilbert Berg",
      "company": "Enquility",
      "dob": "1990-12-05",
      "address": "36 Minna Street, Clarence, Vermont",
      "location": {
        "lat": -27.127468,
        "long": -44.952217
      },
      "about": "Qui adipisicing velit non eu qui fugiat eu esse ut ad laboris proident. Excepteur veniam consequat sunt Lorem nisi eu fugiat labore officia cillum ad enim ullamco irure.",
      "createdAt": "2011-04-27T02:37:00.104Z",
      "updatedAt": "2011-04-28T02:37:00.104Z"
    },
    {
      "id": "627a07167e00ee3a27f38051",
      "email": "duran_garner@minga.camera",
      "username": "duran88",
      "name": "Duran Garner",
      "company": "Minga",
      "dob": "1988-06-11",
      "address": "62 Moore Street, Deltaville, Guam",
      "location": {
        "lat": 39.660321,
        "long": 111.173452
      },
      "about": "Amet cillum do ipsum et tempor nisi nulla proident consectetur veniam. Deserunt dolore cillum dolore duis pariatur aliquip ullamco.",
      "createdAt": "2011-03-10T23:52:08.866Z",
      "updatedAt": "2011-03-11T23:52:08.866Z"
    },
    {
      "id": "627a0716f8d54b550c8d6864",
      "email": "gabrielle_vance@dadabase.club",
      "username": "gabrielle88",
      "name": "Gabrielle Vance",
      "company": "Dadabase",
      "dob": "1988-09-25",
      "address": "6 Morton Street, Brookfield, Maryland",
      "location": {
        "lat": 48.038646,
        "long": 175.769716
      },
      "about": "Duis nisi cillum adipisicing do. Sit consequat esse aliquip aliquip consequat occaecat ad consectetur.",
      "createdAt": "2011-08-25T12:53:44.233Z",
      "updatedAt": "2011-08-26T12:53:44.233Z"
    },
    {
      "id": "627a071677a3799e4567f119",
      "email": "butler_byrd@kage.pt",
      "username": "butler94",
      "name": "Butler Byrd",
      "company": "Kage",
      "dob": "1994-05-18",
      "address": "46 Nautilus Avenue, Joes, Georgia",
      "location": {
        "lat": -64.369002,
        "long": 99.987472
      },
      "about": "Enim pariatur Lorem minim aliqua ad veniam Lorem proident eu dolor anim ullamco. Proident ut quis et occaecat pariatur deserunt.",
      "createdAt": "2012-05-30T19:30:52.790Z",
      "updatedAt": "2012-05-31T19:30:52.790Z"
    },
    {
      "id": "627a07166106995f6a7ed7a0",
      "email": "graciela_hickman@imageflow.online",
      "username": "graciela91",
      "name": "Graciela Hickman",
      "company": "Imageflow",
      "dob": "1991-10-27",
      "address": "27 Varanda Place, Rodanthe, Rhode Island",
      "location": {
        "lat": -60.882882,
        "long": -105.192704
      },
      "about": "Ea id est enim consequat eu ullamco sunt nostrud aliqua proident magna Lorem. Mollit incididunt exercitation labore culpa anim quis in officia adipisicing.",
      "createdAt": "2013-09-06T20:00:50.431Z",
      "updatedAt": "2013-09-07T20:00:50.431Z"
    },
    {
      "id": "627a0716e8450d6d86ba6e4d",
      "email": "doyle_todd@biolive.productions",
      "username": "doyle90",
      "name": "Doyle Todd",
      "company": "Biolive",
      "dob": "1990-12-14",
      "address": "31 Kay Court, Balm, Minnesota",
      "location": {
        "lat": 51.414813,
        "long": -147.627621
      },
      "about": "Enim adipisicing ea proident est cupidatat aliquip esse. Ad ad ad dolor dolore.",
      "createdAt": "2012-07-29T18:51:34.837Z",
      "updatedAt": "2012-07-30T18:51:34.837Z"
    },
    {
      "id": "627a0716440eb01339089988",
      "email": "howell_noble@vetron.microsoft",
      "username": "howell90",
      "name": "Howell Noble",
      "company": "Vetron",
      "dob": "1990-05-15",
      "address": "16 Vanderbilt Street, Dixie, Massachusetts",
      "location": {
        "lat": -55.660035,
        "long": 116.775561
      },
      "about": "Exercitation velit deserunt consequat cupidatat amet tempor in labore adipisicing consequat consectetur occaecat non magna. Magna aute est anim est anim velit aliquip tempor eiusmod ea officia aliquip incididunt in.",
      "createdAt": "2010-09-06T00:34:05.875Z",
      "updatedAt": "2010-09-07T00:34:05.875Z"
    },
    {
      "id": "627a0716e64dc349ee59805b",
      "email": "staci_mcclure@xyqag.dabur",
      "username": "staci94",
      "name": "Staci Mcclure",
      "company": "Xyqag",
      "dob": "1994-04-03",
      "address": "61 Hemlock Street, Cade, Arkansas",
      "location": {
        "lat": 65.352518,
        "long": -154.147027
      },
      "about": "Dolor culpa voluptate proident incididunt ad in deserunt nulla tempor. Ut proident ut officia commodo reprehenderit laborum ea fugiat amet.",
      "createdAt": "2013-09-27T07:56:18.910Z",
      "updatedAt": "2013-09-28T07:56:18.910Z"
    },
    {
      "id": "627a0716dd43c572c2df44f5",
      "email": "estelle_morrow@pivitol.williamhill",
      "username": "estelle88",
      "name": "Estelle Morrow",
      "company": "Pivitol",
      "dob": "1988-10-19",
      "address": "53 Gardner Avenue, Cecilia, Delaware",
      "location": {
        "lat": 1.098009,
        "long": 141.028622
      },
      "about": "Dolor pariatur sint deserunt aliquip. Laborum exercitation eu elit pariatur occaecat ex sit dolore qui dolore amet commodo laborum mollit.",
      "createdAt": "2013-11-14T22:40:52.599Z",
      "updatedAt": "2013-11-15T22:40:52.599Z"
    },
    {
      "id": "627a0716a8ff8cd735121202",
      "email": "santana_casey@slambda.site",
      "username": "santana94",
      "name": "Santana Casey",
      "company": "Slambda",
      "dob": "1994-10-26",
      "address": "57 Louisa Street, Galesville, Northern Mariana Islands",
      "location": {
        "lat": -71.220388,
        "long": -130.886236
      },
      "about": "Cupidatat adipisicing velit aliquip quis ea eu sit ipsum cupidatat. Ex tempor incididunt ullamco elit exercitation eiusmod exercitation ut eiusmod ullamco magna non.",
      "createdAt": "2011-12-21T13:53:00.065Z",
      "updatedAt": "2011-12-22T13:53:00.065Z"
    },
    {
      "id": "627a07168293038b6dbedcb3",
      "email": "dickson_bradford@applidec.gs",
      "username": "dickson90",
      "name": "Dickson Bradford",
      "company": "Applidec",
      "dob": "1990-12-31",
      "address": "25 Garden Place, Florence, Michigan",
      "location": {
        "lat": -3.834575,
        "long": 87.569178
      },
      "about": "Ex fugiat cillum fugiat excepteur. Sunt exercitation elit cillum duis elit mollit voluptate sunt occaecat consectetur dolor.",
      "createdAt": "2012-07-29T19:22:00.110Z",
      "updatedAt": "2012-07-30T19:22:00.110Z"
    },
    {
      "id": "627a07163e02ab963851e8fd",
      "email": "figueroa_jacobson@accufarm.rs",
      "username": "figueroa93",
      "name": "Figueroa Jacobson",
      "company": "Accufarm",
      "dob": "1993-09-04",
      "address": "33 Powell Street, Carrsville, Louisiana",
      "location": {
        "lat": 45.612408,
        "long": -101.109894
      },
      "about": "Sint aliqua eu tempor ipsum nisi id. In laborum veniam cillum dolor elit sit enim pariatur irure duis cillum duis irure.",
      "createdAt": "2011-04-23T22:07:36.151Z",
      "updatedAt": "2011-04-24T22:07:36.151Z"
    },
    {
      "id": "627a0716ad2511860f905b48",
      "email": "acosta_foley@gazak.movie",
      "username": "acosta88",
      "name": "Acosta Foley",
      "company": "Gazak",
      "dob": "1988-05-15",
      "address": "83 Campus Road, Floris, District Of Columbia",
      "location": {
        "lat": -38.490698,
        "long": 164.035428
      },
      "about": "Aliqua cupidatat elit non aliquip Lorem qui do irure. Deserunt esse velit irure commodo occaecat sit adipisicing irure amet duis magna elit mollit adipisicing.",
      "createdAt": "2012-12-20T07:49:16.129Z",
      "updatedAt": "2012-12-21T07:49:16.129Z"
    },
    {
      "id": "627a07168c6d6312ff5b4bb4",
      "email": "constance_thomas@franscene.ag",
      "username": "constance92",
      "name": "Constance Thomas",
      "company": "Franscene",
      "dob": "1992-07-31",
      "address": "57 Gem Street, Falmouth, Colorado",
      "location": {
        "lat": 21.053671,
        "long": -102.148729
      },
      "about": "Sint laborum minim eiusmod id fugiat dolor. Nulla ea do aute tempor culpa est proident esse duis enim anim consequat consequat.",
      "createdAt": "2010-03-05T21:18:01.946Z",
      "updatedAt": "2010-03-06T21:18:01.946Z"
    },
    {
      "id": "627a07161e8547bf139fb535",
      "email": "adeline_maxwell@mitroc.jcb",
      "username": "adeline92",
      "name": "Adeline Maxwell",
      "company": "Mitroc",
      "dob": "1992-10-27",
      "address": "8 Tompkins Place, Lithium, Alabama",
      "location": {
        "lat": 17.598082,
        "long": -65.601331
      },
      "about": "Veniam culpa ut eiusmod amet in magna dolore mollit ullamco cillum cillum pariatur adipisicing esse. Eiusmod non exercitation laboris proident anim velit amet est proident minim.",
      "createdAt": "2014-10-24T13:39:35.947Z",
      "updatedAt": "2014-10-25T13:39:35.947Z"
    },
    {
      "id": "627a071670d4fd5447364032",
      "email": "meagan_stephens@sureplex.ky",
      "username": "meagan91",
      "name": "Meagan Stephens",
      "company": "Sureplex",
      "dob": "1991-08-06",
      "address": "11 Rogers Avenue, Hayes, Nevada",
      "location": {
        "lat": 22.413445,
        "long": -57.243326
      },
      "about": "Pariatur nostrud est dolore et aliqua. Magna est labore id qui nisi cupidatat quis velit ullamco consequat in occaecat.",
      "createdAt": "2011-08-06T16:08:04.176Z",
      "updatedAt": "2011-08-07T16:08:04.176Z"
    },
    {
      "id": "627a07163704c4066f809bf2",
      "email": "lakisha_phelps@gink.trading",
      "username": "lakisha90",
      "name": "Lakisha Phelps",
      "company": "Gink",
      "dob": "1990-08-23",
      "address": "43 Lester Court, Marion, South Carolina",
      "location": {
        "lat": 64.330516,
        "long": -90.654312
      },
      "about": "Irure officia officia consequat cillum dolore consequat eu. Occaecat reprehenderit commodo reprehenderit incididunt nostrud.",
      "createdAt": "2013-05-03T11:13:26.913Z",
      "updatedAt": "2013-05-04T11:13:26.913Z"
    },
    {
      "id": "627a071687380f8e2159fbd0",
      "email": "patsy_lynch@enervate.walter",
      "username": "patsy89",
      "name": "Patsy Lynch",
      "company": "Enervate",
      "dob": "1989-02-25",
      "address": "88 Karweg Place, Urbana, Arizona",
      "location": {
        "lat": -54.920611,
        "long": 72.911073
      },
      "about": "Ea pariatur amet velit duis sint magna. Dolore sunt magna veniam mollit.",
      "createdAt": "2013-08-22T01:46:02.572Z",
      "updatedAt": "2013-08-23T01:46:02.572Z"
    },
    {
      "id": "627a0716ac94d6acb9d79ede",
      "email": "mays_castillo@senmei.ng",
      "username": "mays88",
      "name": "Mays Castillo",
      "company": "Senmei",
      "dob": "1988-01-23",
      "address": "63 Whitney Avenue, Denio, Kentucky",
      "location": {
        "lat": -0.608628,
        "long": -168.167646
      },
      "about": "Exercitation est deserunt cupidatat minim aliqua cillum consequat occaecat officia reprehenderit. Ullamco veniam officia id Lorem deserunt anim officia occaecat ullamco laboris.",
      "createdAt": "2011-11-25T01:07:35.996Z",
      "updatedAt": "2011-11-26T01:07:35.996Z"
    },
    {
      "id": "627a0716ed4dea4c26c600f9",
      "email": "mari_avila@terrago.nf",
      "username": "mari93",
      "name": "Mari Avila",
      "company": "Terrago",
      "dob": "1993-02-21",
      "address": "55 Ferry Place, Aurora, Missouri",
      "location": {
        "lat": 32.758994,
        "long": -124.518228
      },
      "about": "Ullamco adipisicing eu adipisicing proident velit tempor adipisicing. Mollit anim nulla proident dolore labore est veniam nostrud est et sit ex mollit.",
      "createdAt": "2013-11-20T15:00:42.706Z",
      "updatedAt": "2013-11-21T15:00:42.706Z"
    },
    {
      "id": "627a0716ff421ab872fe1aac",
      "email": "moses_duran@frenex.fr",
      "username": "moses91",
      "name": "Moses Duran",
      "company": "Frenex",
      "dob": "1991-07-21",
      "address": "40 Waldane Court, Matthews, Connecticut",
      "location": {
        "lat": -50.090442,
        "long": -21.977737
      },
      "about": "Dolore incididunt dolore dolor eiusmod labore magna veniam ex reprehenderit. Culpa exercitation minim eiusmod labore ullamco pariatur Lorem non.",
      "createdAt": "2014-11-07T09:04:19.701Z",
      "updatedAt": "2014-11-08T09:04:19.701Z"
    },
    {
      "id": "627a0716887f5b1f797a1966",
      "email": "middleton_rush@realmo.vegas",
      "username": "middleton90",
      "name": "Middleton Rush",
      "company": "Realmo",
      "dob": "1990-03-30",
      "address": "79 Batchelder Street, Austinburg, Alaska",
      "location": {
        "lat": 83.894252,
        "long": -174.104592
      },
      "about": "Fugiat in cillum ullamco proident sint mollit ut sunt. Pariatur irure eiusmod dolore tempor laborum commodo.",
      "createdAt": "2010-09-12T15:25:12.512Z",
      "updatedAt": "2010-09-13T15:25:12.512Z"
    },
    {
      "id": "627a0716dd90a8991900330a",
      "email": "jennifer_giles@gallaxia.bbc",
      "username": "jennifer89",
      "name": "Jennifer Giles",
      "company": "Gallaxia",
      "dob": "1989-05-03",
      "address": "72 Eldert Lane, Sunbury, Montana",
      "location": {
        "lat": 64.915385,
        "long": 116.901722
      },
      "about": "Excepteur nostrud excepteur qui anim sunt esse adipisicing. Deserunt ipsum do fugiat exercitation est proident commodo laborum elit Lorem.",
      "createdAt": "2013-03-04T20:03:25.774Z",
      "updatedAt": "2013-03-05T20:03:25.774Z"
    },
    {
      "id": "627a07163f1cdab5b7379939",
      "email": "castaneda_woods@otherside.lds",
      "username": "castaneda88",
      "name": "Castaneda Woods",
      "company": "Otherside",
      "dob": "1988-06-30",
      "address": "38 Onderdonk Avenue, Coyote, Wisconsin",
      "location": {
        "lat": -41.744827,
        "long": 127.312658
      },
      "about": "Mollit non irure consequat amet fugiat non minim mollit. Consectetur enim culpa Lorem nostrud cupidatat non est sint dolore irure.",
      "createdAt": "2013-08-25T23:40:46.952Z",
      "updatedAt": "2013-08-26T23:40:46.952Z"
    },
    {
      "id": "627a07167e217ef57af6c8ba",
      "email": "cherie_fitzpatrick@spacewax.school",
      "username": "cherie91",
      "name": "Cherie Fitzpatrick",
      "company": "Spacewax",
      "dob": "1991-09-20",
      "address": "86 Schweikerts Walk, Onton, West Virginia",
      "location": {
        "lat": -65.058869,
        "long": -147.086085
      },
      "about": "Ullamco non esse ut occaecat id Lorem. Consectetur aute culpa velit enim sit minim sint velit excepteur laboris proident aliquip veniam sit.",
      "createdAt": "2013-10-03T06:47:04.853Z",
      "updatedAt": "2013-10-04T06:47:04.853Z"
    },
    {
      "id": "627a07165e5ef6d1cc2d3986",
      "email": "wagner_battle@qualitern.gq",
      "username": "wagner93",
      "name": "Wagner Battle",
      "company": "Qualitern",
      "dob": "1993-01-31",
      "address": "17 Manor Court, Saticoy, Nebraska",
      "location": {
        "lat": -7.282713,
        "long": -167.372887
      },
      "about": "Incididunt non est exercitation ad magna aute minim. Ex reprehenderit dolore do exercitation ad fugiat ullamco consectetur consectetur velit duis et deserunt dolore.",
      "createdAt": "2014-04-17T19:19:00.957Z",
      "updatedAt": "2014-04-18T19:19:00.957Z"
    },
    {
      "id": "627a0716b521824c756de47b",
      "email": "kristy_conrad@unisure.reviews",
      "username": "kristy93",
      "name": "Kristy Conrad",
      "company": "Unisure",
      "dob": "1993-10-15",
      "address": "98 Horace Court, Cartwright, Maine",
      "location": {
        "lat": 77.341717,
        "long": -30.201269
      },
      "about": "Aute tempor reprehenderit ad reprehenderit in qui commodo nisi et duis dolor Lorem. Nostrud commodo dolor et ea sunt labore magna eiusmod occaecat amet qui nulla ex.",
      "createdAt": "2014-11-19T09:34:50.667Z",
      "updatedAt": "2014-11-20T09:34:50.667Z"
    },
    {
      "id": "627a0716b17659fed17807da",
      "email": "lynn_kirkland@blurrybus.lease",
      "username": "lynn89",
      "name": "Lynn Kirkland",
      "company": "Blurrybus",
      "dob": "1989-03-01",
      "address": "26 Durland Place, Idamay, North Dakota",
      "location": {
        "lat": 4.966626,
        "long": 63.138579
      },
      "about": "Minim commodo elit dolor est dolor consectetur. Sint anim adipisicing Lorem qui minim laboris minim eu.",
      "createdAt": "2013-05-25T17:44:35.994Z",
      "updatedAt": "2013-05-26T17:44:35.994Z"
    },
    {
      "id": "627a0716e142059db388ce82",
      "email": "johns_norman@quarmony.tui",
      "username": "johns93",
      "name": "Johns Norman",
      "company": "Quarmony",
      "dob": "1993-05-11",
      "address": "23 Belmont Avenue, Crumpler, Ohio",
      "location": {
        "lat": -17.358083,
        "long": 155.355809
      },
      "about": "Sit esse elit est eu exercitation mollit deserunt reprehenderit incididunt nisi. Laboris laborum laborum excepteur sint.",
      "createdAt": "2014-12-10T01:35:19.597Z",
      "updatedAt": "2014-12-11T01:35:19.597Z"
    },
    {
      "id": "627a0716a637785517e70fc0",
      "email": "floyd_knapp@colaire.lv",
      "username": "floyd91",
      "name": "Floyd Knapp",
      "company": "Colaire",
      "dob": "1991-05-24",
      "address": "50 Dover Street, Hayden, New Jersey",
      "location": {
        "lat": 59.369411,
        "long": -89.982111
      },
      "about": "Occaecat Lorem occaecat ex exercitation commodo duis aute qui eu consectetur ipsum. Lorem aliquip labore cillum adipisicing consectetur Lorem magna.",
      "createdAt": "2010-10-18T22:36:10.822Z",
      "updatedAt": "2010-10-19T22:36:10.822Z"
    },
    {
      "id": "627a0716f146abc5ff978e19",
      "email": "barr_lamb@furnitech.canon",
      "username": "barr89",
      "name": "Barr Lamb",
      "company": "Furnitech",
      "dob": "1989-09-19",
      "address": "78 Eagle Street, Rew, North Carolina",
      "location": {
        "lat": 49.208155,
        "long": -29.485312
      },
      "about": "Lorem sunt pariatur laborum dolor adipisicing. Cupidatat ullamco ad cupidatat aute in incididunt.",
      "createdAt": "2014-04-07T18:27:42.446Z",
      "updatedAt": "2014-04-08T18:27:42.446Z"
    },
    {
      "id": "627a0716ca8c37de999a214c",
      "email": "frye_barber@aquoavo.hu",
      "username": "frye90",
      "name": "Frye Barber",
      "company": "Aquoavo",
      "dob": "1990-01-17",
      "address": "74 Vanderbilt Avenue, Cazadero, Texas",
      "location": {
        "lat": 25.458987,
        "long": -154.549417
      },
      "about": "Non non amet exercitation proident sit. Irure consequat minim cupidatat duis consequat.",
      "createdAt": "2014-04-05T01:06:58.743Z",
      "updatedAt": "2014-04-06T01:06:58.743Z"
    },
    {
      "id": "627a07161077991617ae1445",
      "email": "ginger_townsend@quizmo.network",
      "username": "ginger91",
      "name": "Ginger Townsend",
      "company": "Quizmo",
      "dob": "1991-06-20",
      "address": "36 Kent Street, Herlong, California",
      "location": {
        "lat": -5.459097,
        "long": -148.396841
      },
      "about": "Dolore amet commodo veniam quis ex consequat nostrud. Cupidatat qui non duis ullamco in.",
      "createdAt": "2013-04-13T19:45:57.111Z",
      "updatedAt": "2013-04-14T19:45:57.111Z"
    },
    {
      "id": "627a0716f963b24d3c252f77",
      "email": "marlene_rogers@biohab.pro",
      "username": "marlene88",
      "name": "Marlene Rogers",
      "company": "Biohab",
      "dob": "1988-11-26",
      "address": "9 Ryder Street, Riverton, Pennsylvania",
      "location": {
        "lat": 65.517062,
        "long": -16.122168
      },
      "about": "Adipisicing consectetur non aute dolor incididunt in exercitation id. Dolore duis minim quis in quis nulla officia ex.",
      "createdAt": "2014-03-13T01:17:42.467Z",
      "updatedAt": "2014-03-14T01:17:42.467Z"
    },
    {
      "id": "627a0716e1aef361cf37d562",
      "email": "sallie_walter@elentrix.guitars",
      "username": "sallie94",
      "name": "Sallie Walter",
      "company": "Elentrix",
      "dob": "1994-08-20",
      "address": "45 Ebony Court, Hilltop, American Samoa",
      "location": {
        "lat": -33.292688,
        "long": -86.365831
      },
      "about": "Amet nulla dolore do ipsum labore eiusmod. Non ex Lorem nisi irure.",
      "createdAt": "2011-08-24T15:33:53.676Z",
      "updatedAt": "2011-08-25T15:33:53.676Z"
    },
    {
      "id": "627a071681854412ca30be3e",
      "email": "price_watson@euron.schule",
      "username": "price90",
      "name": "Price Watson",
      "company": "Euron",
      "dob": "1990-02-12",
      "address": "50 Dean Street, Jardine, Puerto Rico",
      "location": {
        "lat": 69.493359,
        "long": 162.156333
      },
      "about": "Qui voluptate nisi est officia aliquip reprehenderit dolore nisi mollit sint cupidatat elit eiusmod laboris. Exercitation elit magna nisi fugiat aute et quis occaecat exercitation cupidatat est proident magna.",
      "createdAt": "2011-05-17T14:18:03.819Z",
      "updatedAt": "2011-05-18T14:18:03.819Z"
    },
    {
      "id": "627a0716a6093472b250f238",
      "email": "alta_burke@grainspot.bg",
      "username": "alta89",
      "name": "Alta Burke",
      "company": "Grainspot",
      "dob": "1989-06-04",
      "address": "93 Story Court, Bakersville, Tennessee",
      "location": {
        "lat": -77.227721,
        "long": 165.879579
      },
      "about": "Commodo sunt adipisicing mollit voluptate veniam non sint id fugiat Lorem duis. Do ipsum deserunt elit dolore officia sint sint dolor.",
      "createdAt": "2014-10-01T15:15:47.358Z",
      "updatedAt": "2014-10-02T15:15:47.358Z"
    },
    {
      "id": "627a0716b63920adbabb23a7",
      "email": "hoffman_bennett@kneedles.la",
      "username": "hoffman91",
      "name": "Hoffman Bennett",
      "company": "Kneedles",
      "dob": "1991-11-11",
      "address": "93 Dewey Place, Brogan, Palau",
      "location": {
        "lat": 53.965857,
        "long": 35.273624
      },
      "about": "Esse mollit incididunt ea aliquip sunt culpa elit eu aute ad reprehenderit ea aliquip. Excepteur laborum commodo aliquip qui pariatur consectetur voluptate sunt dolore.",
      "createdAt": "2013-03-06T09:53:43.265Z",
      "updatedAt": "2013-03-07T09:53:43.265Z"
    },
    {
      "id": "627a0716dbb0486098adaa88",
      "email": "mayra_ramirez@comcur.pf",
      "username": "mayra93",
      "name": "Mayra Ramirez",
      "company": "Comcur",
      "dob": "1993-02-06",
      "address": "87 Grove Street, Twilight, Oklahoma",
      "location": {
        "lat": 86.294875,
        "long": -106.468887
      },
      "about": "Quis elit elit amet mollit id consectetur pariatur ut laborum. Aliqua sint anim do deserunt quis anim eiusmod incididunt minim velit id.",
      "createdAt": "2014-10-22T05:11:37.555Z",
      "updatedAt": "2014-10-23T05:11:37.555Z"
    },
    {
      "id": "627a0716f84fda507faee457",
      "email": "justice_mckee@geekola.th",
      "username": "justice90",
      "name": "Justice Mckee",
      "company": "Geekola",
      "dob": "1990-07-08",
      "address": "8 Tiffany Place, Rutherford, Kansas",
      "location": {
        "lat": 76.253248,
        "long": 53.078404
      },
      "about": "Cupidatat pariatur officia adipisicing velit voluptate excepteur nisi duis ullamco incididunt in nostrud qui. Est fugiat culpa ex dolore aliqua et sit consectetur consectetur adipisicing irure dolore eiusmod.",
      "createdAt": "2014-06-28T01:23:17.324Z",
      "updatedAt": "2014-06-29T01:23:17.324Z"
    },
    {
      "id": "627a0716b9b6730f3ad1f172",
      "email": "marva_buck@bluegrain.memorial",
      "username": "marva88",
      "name": "Marva Buck",
      "company": "Bluegrain",
      "dob": "1988-05-13",
      "address": "84 Osborn Street, Dunlo, Oregon",
      "location": {
        "lat": 82.105855,
        "long": 47.597387
      },
      "about": "Est ut consequat labore laborum adipisicing dolore elit laboris magna anim dolore do ullamco. Fugiat id occaecat ea quis commodo aliquip laborum.",
      "createdAt": "2010-03-19T12:47:20.862Z",
      "updatedAt": "2010-03-20T12:47:20.862Z"
    },
    {
      "id": "627a0716f69d3c72891a02ce",
      "email": "baker_carroll@comvex.mm",
      "username": "baker93",
      "name": "Baker Carroll",
      "company": "Comvex",
      "dob": "1993-02-22",
      "address": "2 Milford Street, Iola, Wyoming",
      "location": {
        "lat": 48.949274,
        "long": 114.573151
      },
      "about": "Consectetur anim nostrud minim velit. Nulla ea veniam incididunt nulla amet do mollit consequat commodo velit non dolor voluptate non.",
      "createdAt": "2014-05-05T23:36:55.751Z",
      "updatedAt": "2014-05-06T23:36:55.751Z"
    }
  ]
}
